deep_compend/__init__.py
deep_compend/cli/__init__.py
deep_compend/cli/cli.py
deep_compend/cli/config.py
deep_compend/cli/subcommands.py
deep_compend/core/__init__.py
deep_compend/core/configs.py
deep_compend/core/summarizer.py
deep_compend/extractors/__init__.py
deep_compend/extractors/keywords_extractor.py
deep_compend/extractors/pdf_extractor.py
deep_compend/text_preprocessing/__init__.py
deep_compend/text_preprocessing/cleaning.py
deep_compend/text_preprocessing/prettify.py
deep_compend/utils/__init__.py
deep_compend/utils/downloads.py
deep_compend/utils/metrics.py
deep_compend-0.1.2.dist-info/licenses/LICENSE.txt
deep_compend-0.1.2.dist-info/METADATA
deep_compend-0.1.2.dist-info/WHEEL
deep_compend-0.1.2.dist-info/entry_points.txt
deep_compend-0.1.2.dist-info/top_level.txt
deep_compend-0.1.2.dist-info/RECORD
