Metadata-Version: 2.4
Name: deep-compend
Version: 0.1.2
Summary: Library for scientific PDF-articles summarization
Author-email: Sergey Polivin <s.polivin@gmail.com>
License: MIT
Project-URL: Homepage, https://github.com/spolivin/deep-compend
Project-URL: Issues, https://github.com/spolivin/deep-compend/issues
Project-URL: Pull-requests, https://github.com/spolivin/deep-compend/pulls
Project-URL: Source, https://github.com/spolivin/deep-compend/tree/master/deep_compend
Keywords: summarization,arxiv,NLP,transformers
Classifier: Programming Language :: Python :: 3
Classifier: License :: OSI Approved :: MIT License
Classifier: Operating System :: OS Independent
Classifier: Development Status :: 3 - Alpha
Requires-Python: >=3.8
License-File: LICENSE.txt
Requires-Dist: torch>=2.6.0
Requires-Dist: transformers>=4.50.0
Requires-Dist: peft>=0.15.0
Requires-Dist: nltk>=3.9.1
Requires-Dist: pymupdf>=1.25.4
Requires-Dist: spacy>=3.8.4
Requires-Dist: requests>=2.32.3
Provides-Extra: test
Requires-Dist: pytest>=8.3.5; extra == "test"
Provides-Extra: build
Requires-Dist: setuptools; extra == "build"
Requires-Dist: wheel; extra == "build"
Requires-Dist: build; extra == "build"
Requires-Dist: twine; extra == "build"
Provides-Extra: linters
Requires-Dist: black; extra == "linters"
Requires-Dist: isort; extra == "linters"
Requires-Dist: pre-commit; extra == "linters"
Dynamic: license-file
